flask_bcrypt.py
Bcrypt_Flask-1.0.2.dist-info/LICENSE
Bcrypt_Flask-1.0.2.dist-info/METADATA
Bcrypt_Flask-1.0.2.dist-info/WHEEL
Bcrypt_Flask-1.0.2.dist-info/top_level.txt
Bcrypt_Flask-1.0.2.dist-info/RECORD
